{
    "startDate": "Tuesday 13 September 2022",
    "countries": {
        "Angola": 1,
        "Belgium": 1,
        "Brazil": 3,
        "Canada": 1,
        "China": 5,
        "Chinese Taiwan": 1,
        "Egypt": 1,
        "Georgia": 1,
        "Iraq": 1,
        "Israel": 1,
        "Korea": 1,
        "Philippines": 1,
        "Russia": 1,
        "South Africa": 1,
        "Spain": 2,
        "Trinidad and Tobago": 1,
        "Turkey": 2,
        "USA": 11,
        "Uzbekistan": 1
    }
}